[
    {
      "Week": 1,
      "Incoming Orders from Distributor": 30,
      "Production": 30,
      "Inventory": 50,
      "InventoryUnitCost": 1,
      "InventoryCost": 50,
      "Placed Orders": 0,
      "Shipment to Distributor": 30,
      "Backorders": 0,
      "BackOrderUnitCost": 5,
      "Backorder Cost": 0,
      "ManufacturerCost": 50,
      "CummManfCost": 50
    },
    {
      "Week": 2,
      "Incoming Orders from Distributor": 35,
      "Production": 30,
      "Inventory": 50,
      "InventoryUnitCost": 1,
      "InventoryCost": 50,
      "Placed Orders": 0,
      "Shipment to Distributor": 30,
      "Backorders": 5,
      "BackOrderUnitCost": 5,
      "Backorder Cost": 25,
      "ManufacturerCost": 75,
      "CummManfCost": 125
    },
    {
      "Week": 3,
      "Incoming Orders from Distributor": 40,
      "Production": 30,
      "Inventory": 45,
      "InventoryUnitCost": 1,
      "InventoryCost": 45,
      "Placed Orders": 0,
      "Shipment to Distributor": 35,
      "Backorders": 5,
      "BackOrderUnitCost": 5,
      "Backorder Cost": 25,
      "ManufacturerCost": 70,
      "CummManfCost": 195
    },
    {
      "Week": 4,
      "Incoming Orders from Distributor": 45,
      "Production": 30,
      "Inventory": 40,
      "InventoryUnitCost": 1,
      "InventoryCost": 40,
      "Placed Orders": 0,
      "Shipment to Distributor": 40,
      "Backorders": 5,
      "BackOrderUnitCost": 5,
      "Backorder Cost": 25,
      "ManufacturerCost": 65,
      "CummManfCost": 260
    },
    {
      "Week": 5,
      "Incoming Orders from Distributor": 50,
      "Production": 30,
      "Inventory": 40,
      "InventoryUnitCost": 1,
      "InventoryCost": 40,
      "Placed Orders": 0,
      "Shipment to Distributor": 45,
      "Backorders": 5,
      "BackOrderUnitCost": 5,
      "Backorder Cost": 25,
      "ManufacturerCost": 65,
      "CummManfCost": 325
    },
    {
      "Week": 6,
      "Incoming Orders from Distributor": 45,
      "Production": 30,
      "Inventory": 35,
      "InventoryUnitCost": 1,
      "InventoryCost": 35,
      "Placed Orders": 0,
      "Shipment to Distributor": 40,
      "Backorders": 5,
      "BackOrderUnitCost": 5,
      "Backorder Cost": 25,
      "ManufacturerCost": 60,
      "CummManfCost": 385
    },
    {
      "Week": 7,
      "Incoming Orders from Distributor": 40,
      "Production": 30,
      "Inventory": 35,
      "InventoryUnitCost": 1,
      "InventoryCost": 35,
      "Placed Orders": 0,
      "Shipment to Distributor": 35,
      "Backorders": 5,
      "BackOrderUnitCost": 5,
      "Backorder Cost": 25,
      "ManufacturerCost": 60,
      "CummManfCost": 445
    },
    {
      "Week": 8,
      "Incoming Orders from Distributor": 35,
      "Production": 30,
      "Inventory": 30,
      "InventoryUnitCost": 1,
      "InventoryCost": 30,
      "Placed Orders": 0,
      "Shipment to Distributor": 30,
      "Backorders": 5,
      "BackOrderUnitCost": 5,
      "Backorder Cost": 25,
      "ManufacturerCost": 55,
      "CummManfCost": 500
    }
  ]